Metadata-Version: 2.1
Name: launchchess
Version: 0.1.1
Summary: Play chess on a Launchpad
Home-page: https://github.com/quaternionmedia/launchchess-python
Author: Quaternion Media
Author-email: info@quaternion.media
License: MIT
Platform: UNKNOWN
Classifier: Programming Language :: Python :: 3
Classifier: License :: OSI Approved :: MIT License
Classifier: Operating System :: OS Independent
Requires-Python: >=3.6
License-File: LICENSE.txt
